mtmeastmoney/__init__.py
mtmeastmoney/auth.py
mtmeastmoney/common.py
mtmeastmoney/eastmoney.py
mtmeastmoney/strategies.py
mtmeastmoney-1.2.1.dist-info/licenses/LICENSE
mtmeastmoney-1.2.1.dist-info/METADATA
mtmeastmoney-1.2.1.dist-info/WHEEL
mtmeastmoney-1.2.1.dist-info/top_level.txt
mtmeastmoney-1.2.1.dist-info/RECORD
