Metadata-Version: 2.4
Name: mtmeastmoney
Version: 1.2.1
Summary: A Personal Eastmoney Library
License: MIT License
Classifier: Development Status :: 3 - Alpha
Classifier: Programming Language :: Python :: 3.9
Classifier: Intended Audience :: Developers
Classifier: License :: OSI Approved :: MIT License
Classifier: Operating System :: MacOS
Classifier: Operating System :: POSIX :: Linux
Classifier: Operating System :: Microsoft :: Windows
Requires-Python: >=3.9
License-File: LICENSE
Requires-Dist: ddddocr
Requires-Dist: requests
Requires-Dist: mtmtool
Requires-Dist: pandas
Dynamic: license-file
